.gitignore
README.md
main.py
requirements.txt
setup.py
.vscode/launch.json
api/health_api.py
api/rule_api.py
config/rules/rules_default.yaml
core/rule/rule_engine_manager.py
models/rule_models.py
rule_engine_client_python.egg-info/PKG-INFO
rule_engine_client_python.egg-info/SOURCES.txt
rule_engine_client_python.egg-info/dependency_links.txt
rule_engine_client_python.egg-info/requires.txt
rule_engine_client_python.egg-info/top_level.txt