Metadata-Version: 2.1
Name: rule-engine-client-python
Version: 2.13.0
Summary: Rule Engine
Home-page: UNKNOWN
Author: OpenAPI Generator community
Author-email: team@openapitools.org
License: UNKNOWN
Keywords: OpenAPI,OpenAPI-Generator,Rule Engine
Platform: UNKNOWN
Requires-Python: >=3.6
